autopew/__init__.py
autopew/_version.py
autopew/gui.py
autopew/readlase.py
autopew/registration.py
autopew/session.py
autopew/targets.py
autopew/transform.py
autopew/util.py
autopew/data/20180925_snowy_lines.lase
autopew/data/Autosaved Scan (2018-09-25 13-28-49).scancsv
autopew/data/__pycache__/registration.cpython-36-PYTEST.pyc
autopew/data/__pycache__/registration.cpython-36.pyc
autopew/data/examples/autopew_test.lase
autopew/data/examples/autopew_test.scancsv
autopew/graph/__init__.py
autopew/graph/network.py
autopew/gui/__init__.py
autopew/gui/base.py
autopew/gui/windows.py
autopew/image/__init__.py
autopew/image/base.py
autopew/io/__init__.py
autopew/io/EPMA/JEOL.py
autopew/io/EPMA/__init__.py
autopew/io/laser/__init__.py
autopew/io/laser/chromium.py
autopew/transform/__init__.py
autopew/transform/affine.py
autopew/transform/calibration.py
autopew/transform/vis.py
autopew/util/__init__.py
autopew/util/__int__.py
autopew/util/general.py
autopew/util/meta.py
autopew/util/plot.py
autopew/workflow/__init__.py
autopew-0.1.4.dist-info/LICENSE
autopew-0.1.4.dist-info/METADATA
autopew-0.1.4.dist-info/WHEEL
autopew-0.1.4.dist-info/top_level.txt
autopew-0.1.4.dist-info/RECORD
