Metadata-Version: 2.1
Name: autopew
Version: 0.1.4
Summary: Automating target selection for laser ablation.
Home-page: https://github.com/morganjwilliams/autopew
Author: Morgan Williams
Author-email: morgan.williams@csiro.au
License: CSIRO Modifed MIT/BSD
Keywords: laser ablation,geochemistry
Platform: UNKNOWN
Classifier: Development Status :: 2 - Pre-Alpha
Classifier: Intended Audience :: Science/Research
Classifier: Natural Language :: English
Classifier: Programming Language :: Python :: 3 :: Only
Classifier: Programming Language :: Python :: 3.6
Classifier: Programming Language :: Python :: 3.7
Classifier: Programming Language :: Python :: 3.8
Classifier: Topic :: Scientific/Engineering
Classifier: Topic :: Software Development :: Libraries :: Python Modules
Requires-Dist: pillow
Requires-Dist: ipython
Requires-Dist: networkx
Requires-Dist: numpy
Requires-Dist: matplotlib
Requires-Dist: xlrd
Requires-Dist: pandas
Requires-Dist: scipy
Provides-Extra: dev
Requires-Dist: pytest ; extra == 'dev'
Requires-Dist: versioneer ; extra == 'dev'
Requires-Dist: black ; extra == 'dev'
Requires-Dist: twine ; extra == 'dev'
Requires-Dist: pytest-runner ; extra == 'dev'
Requires-Dist: pytest-cov ; extra == 'dev'
Requires-Dist: coverage ; extra == 'dev'
Requires-Dist: codecov ; extra == 'dev'
Requires-Dist: sphinx-rtd-theme ; extra == 'dev'
Requires-Dist: sphinx-autodoc-annotation ; extra == 'dev'
Requires-Dist: recommonmark ; extra == 'dev'
Provides-Extra: docs
Requires-Dist: sphinx-rtd-theme ; extra == 'docs'
Requires-Dist: sphinx-autodoc-annotation ; extra == 'docs'
Requires-Dist: recommonmark ; extra == 'docs'
